LICENSE.txt
chessy/__init__.py
chessy/core/__init__.py
chessy/core/__main__.py
chessy/core/atkgen.py
chessy/core/board.py
chessy/core/evaluator.py
chessy/core/fen_parser.py
chessy/core/movegen.py
chessy/core/test_atkgen.py
chessy/core/test_board.py
chessy/core/test_evaluator.py
chessy/core/test_fen_parser.py
chessy/core/test_init.py
chessy/core/test_movegen.py
chessy/core/uci.py
chessy/prof/__init__.py
chessy/prof/__main__.py
chessy/project_meta.py
chessy/test_utils.py
chessy/utils.py
pyproject.toml
chessy-0.2.3.dist-info/LICENSE.txt
chessy-0.2.3.dist-info/METADATA
chessy-0.2.3.dist-info/WHEEL
chessy-0.2.3.dist-info/entry_points.txt
chessy-0.2.3.dist-info/RECORD
