Metadata-Version: 2.1
Name: chessy
Version: 0.2.3
Summary: A simple chess engine
Home-page: https://github.com/Guilherme-Vasconcelos/chessy
License: AGPL-3.0-or-later
Keywords: chess
Author: Guilherme Vasconcelos
Requires-Python: >=3.11,<4.0
Classifier: Environment :: Console
Classifier: License :: OSI Approved :: GNU Affero General Public License v3 or later (AGPLv3+)
Classifier: Programming Language :: Python :: 3
Classifier: Programming Language :: Python :: 3.11
Classifier: Topic :: Games/Entertainment :: Board Games
Project-URL: Repository, https://github.com/Guilherme-Vasconcelos/chessy
